p123/.DS_Store
p123/__init__.py
p123-0.0.1.dist-info/METADATA
p123-0.0.1.dist-info/WHEEL
p123-0.0.1.dist-info/RECORD
