Metadata-Version: 2.1
Name: p123
Version: 0.0.1
Summary: Python 123 webdisk client.
Home-page: https://github.com/ChenyangGao/p123client
License: MIT
Keywords: 123,webdisk,client
Author: ChenyangGao
Author-email: wosiwujm@gmail.com
Requires-Python: >=3.12,<4.0
Classifier: Development Status :: 4 - Beta
Classifier: Intended Audience :: Developers
Classifier: License :: OSI Approved :: MIT License
Classifier: Operating System :: OS Independent
Classifier: Programming Language :: Python
Classifier: Programming Language :: Python :: 3
Classifier: Programming Language :: Python :: 3.12
Classifier: Programming Language :: Python :: 3.13
Classifier: Programming Language :: Python :: 3 :: Only
Classifier: Topic :: Software Development
Classifier: Topic :: Software Development :: Libraries
Classifier: Topic :: Software Development :: Libraries :: Python Modules
Requires-Dist: p123client
Project-URL: Documentation, https://p123client.readthedocs.io
Project-URL: Repository, https://github.com/ChenyangGao/p123client
